ofwhich/__init__.py
ofwhich/py.typed
ofwhich-0.1.0.dist-info/METADATA
ofwhich-0.1.0.dist-info/WHEEL
ofwhich-0.1.0.dist-info/licenses/LICENSE
ofwhich-0.1.0.dist-info/RECORD
