Metadata-Version: 2.4
Name: ofwhich
Version: 0.1.0
Summary: Drill-down through your dataframe.
Project-URL: Homepage, https://github.com/em-oaken/ofwhich
Project-URL: Issues, https://github.com/em-oaken/ofwhich/issues
Author-email: Em Oaken <mr.oaken@ik.me>
License-Expression: MIT
License-File: LICENSE
Classifier: Development Status :: 2 - Pre-Alpha
Classifier: Operating System :: OS Independent
Classifier: Programming Language :: Python :: 3
Requires-Python: >=3.12
